[
  {
    "id": 63,
    "name": "Luka Doncic",
    "image": "../images/players/Doncic.png",
    "jersey": 77,
    "game": {
      "PTS": 30,
      "MIN": 34,
      "FGP": 47.4,
      "P3P": 46.2,
      "FTP": 54.5,
      "REB": 8,
      "AST": 15,
      "BLK": 1,
      "STL": 1,
      "PF": 0,
      "TO": 5
    },
    "season": {
      "GP": 31,
      "PPG": 26.6,  
      "MIN": 34.6,
      "FGP": 44.7,
      "P3P": 33.9,
      "FTP": 75.1,
      "REB": 8.3,
      "AST": 7.8,
      "BLK": 0.5,
      "STL": 1.9,
      "PF": 2.6,
      "TO": 3.5
    },
    "career": {
      "GP": 431,
      "PPG": 28.5,  
      "MIN": 34.8,        
      "FGP": 46.8,
      "P3P": 34.7,
      "FTP": 74.8,
      "REB": 8.7,
      "AST": 8.3,
      "BLK": 0.5,
      "STL": 1.2,
      "PF": 2.3,
      "TO": 4.0
    }
  },
  {
    "id": 64,
    "name": "Dorian Finney-Smith",
    "image": "../images/players/Finney-Smith.jpg",
    "jersey": 17,
    "game": {
      "PTS": 8,
      "MIN": 30,
      "FGP": 30.0,
      "P3P": 28.6,
      "FTP": 0,
      "REB": 5,
      "AST": 0,
      "BLK": 0,
      "STL": 0,
      "PF": 1,
      "TO": 2
    },
    "season": {
      "GP": 45,
      "PPG": 8.4,
      "MIN": 27.8,
      "FGP": 44.9,
      "P3P": 40.2,
      "FTP": 66.7,
      "REB": 4.0,
      "AST": 1.4,
      "BLK": 0.3,
      "STL": 0.9,
      "PF": 2.2,
      "TO": 0.9
    },
    "career": {
      "GP": 573,
      "PPG": 8.3,
      "MIN": 27.8,
      "FGP": 43.6,
      "P3P": 35.9,
      "FTP": 71.9,
      "REB": 4.5,
      "AST": 1.4,
      "BLK": 0.4,
      "STL": 0.8,
      "PF": 2.2,
      "TO": 0.9
    }
  },
  {
    "id": 70,
    "name": "Jordan Goodwin",
    "image": "../images/players/Goodwin.png",
    "jersey": 30,
    "game": {
      "PTS": 0,
      "MIN": 0,
      "FGP": 0,
      "P3P": 0,
      "FTP": 0,
      "REB": 0,
      "AST": 0,
      "BLK": 0,
      "STL": 0,
      "PF": 0,
      "TO": 0
    },
    "season": {
      "GP": 8,
      "PPG": 6.1,
      "MIN": 16.9,
      "FGP": 52.5,
      "P3P": 31.3,
      "FTP": 66.7,
      "REB": 3.8,
      "AST": 1.0,
      "BLK": 0.3,
      "STL": 1.3,
      "PF": 1.5,
      "TO": 0.8
    },
    "career": {
      "GP": 129,
      "PPG": 6.4,
      "MIN": 17.8,
      "FGP": 41.1,
      "P3P": 30.8,
      "FTP": 75.6,
      "REB": 3.8,
      "AST": 2.6,
      "BLK": 0.4,
      "STL": 0.9,
      "PF": 1.4,
      "TO": 0.9
    }
  },
  {
    "id": 43,
    "name": "Rui Hachimura",
    "image": "../images/players/Hachimura.png",
    "jersey": 28,
    "game": {
      "PTS": 0,
      "MIN": 0,
      "FGP": 0,
      "P3P": 0,
      "FTP": 0,
      "REB": 0,
      "AST": 0,
      "BLK": 0,
      "STL": 0,
      "PF": 0,
      "TO": 0
    },
    "season": {
      "GP": 50,
      "PPG": 13.3,  
      "MIN": 32.1,
      "FGP": 50.6,
      "P3P": 41.0,
      "FTP": 76.5,
      "REB": 5.2,
      "AST": 1.5,
      "BLK": 0.5,
      "STL": 0.8,
      "PF": 1.8,
      "TO": 0.9
    },
    "career": {
      "GP": 328,
      "PPG": 12.8,  
      "MIN": 27.7,
      "FGP": 49.5,
      "P3P": 37.9,
      "FTP": 76.3,
      "REB": 4.9,
      "AST": 1.3,
      "BLK": 0.3,
      "STL": 0.6,
      "PF": 1.7,
      "TO": 0.9
    }
  },
  {
    "id": 52,
    "name": "Jaxson Hayes",
    "image": "../images/players/Hayes.png",
    "jersey": 10,
    "game": {
      "PTS": 19,
      "MIN": 24,
      "FGP": 100.0,
      "P3P": 0,
      "FTP": 100.0,
      "REB": 10,
      "AST": 0,
      "BLK": 0,
      "STL": 0,
      "PF": 5,
      "TO": 1
    },
    "season": {
      "GP": 39,
      "PPG": 6.4,  
      "MIN": 18.8,
      "FGP": 71.8,
      "P3P": 0,
      "FTP": 72.6,
      "REB": 4.5,
      "AST": 1.0,
      "BLK": 1.0,
      "STL": 0.6,
      "PF": 2.2,
      "TO": 0.7
    },
    "career": {
      "GP": 350,
      "PPG": 6.7, 
      "MIN": 16.2,
      "FGP": 64.4,
      "P3P": 26.3,
      "FTP": 70.9,
      "REB": 3.9,
      "AST": 0.7,  
      "BLK": 0.7,
      "STL": 0.5,
      "PF": 2.0,
      "TO": 0.7
    }
  },
  {
    "id": 57,
    "name": "Bronny James",
    "image": "../images/players/Bronny.png",
    "jersey": 9,
    "game": {
      "PTS": 2,
      "MIN": 4,
      "FGP": 33.3,
      "P3P": 0,
      "FTP": 0,
      "REB": 1,
      "AST": 0,
      "BLK": 0,
      "STL": 0,
      "PF": 1,
      "TO": 0
    },
    "season": {
      "GP": 18,
      "PPG": 1.4,
      "MIN": 4.2,
      "FGP": 25.8,
      "P3P": 20.0,
      "FTP": 66.7,
      "REB": 0.4,
      "AST": 0.4,
      "BLK": 0.1,
      "STL": 0.2,
      "PF": 0.3,
      "TO": 0.3
    },
    "career": {
      "GP": 18,
      "PPG": 1.4,
      "MIN": 4.2,
      "FGP": 25.8,
      "P3P": 20.0,
      "FTP": 66.7,
      "REB": 0.4,
      "AST": 0.4,
      "BLK": 0.1,
      "STL": 0.2,
      "PF": 0.3,
      "TO": 0.3
    }
  },
  {
    "id": 12,
    "name": "Lebron James",
    "image": "../images/players/James.png",
    "jersey": 23,
    "game": {
      "PTS": 34,
      "MIN": 33,
      "FGP": 55.6,
      "P3P": 50.0,
      "FTP": 100.0,
      "REB": 8,
      "AST": 6,
      "BLK": 2,
      "STL": 1,
      "PF": 1,
      "TO": 4
    },
    "season": {
      "GP": 56,
      "PPG": 24.9,  
      "MIN": 34.7,
      "FGP": 51.9,
      "P3P": 39.4,
      "FTP": 77.6,
      "REB": 8.0,
      "AST": 8.5,
      "BLK": 0.6,
      "STL": 0.9,
      "PF": 1.4,
      "TO": 4.0
    },
    "career": {
      "GP": 1548,
      "PPG": 27.0,
      "MIN": 37.8,
      "FGP": 50.7,
      "P3P": 35.0,
      "FTP": 73.7,
      "REB": 7.5,
      "AST": 7.4,
      "BLK": 0.7,
      "STL": 1.5,
      "PF": 1.8,
      "TO": 3.5
    }
  },
  {
    "id": 67,
    "name": "Trey Jemison III",
    "image": "../images/players/Jemison.png",
    "jersey": 55,
    "game": {
      "PTS": 4,
      "MIN": 17,
      "FGP": 100.0,
      "P3P": 0,
      "FTP": 0,
      "REB": 5,
      "AST": 2,
      "BLK": 0,
      "STL": 0,
      "PF": 2,
      "TO": 0
    },
    "season": {
      "GP": 28,
      "PPG": 2.7,
      "MIN": 10.8,
      "FGP": 54.2,
      "P3P": 0,
      "FTP": 37.9,
      "REB": 2.9,
      "AST": 0.5,
      "BLK": 0.4,
      "STL": 0.3,
      "PF": 1.9,
      "TO": 0.5
    },
    "career": {
      "GP": 53,
      "PPG": 4.6,
      "MIN": 16.5,
      "FGP": 54.9,
      "P3P": 0,
      "FTP": 59.3,
      "REB": 4.0,
      "AST": 0.8,
      "BLK": 0.8,
      "STL": 0.4,
      "PF": 2.3,
      "TO": 0.9
    }
  },
  {
    "id": 65,
    "name": "Maxi Kleber",
    "image": "../images/players/Kleber.jpg",
    "jersey": 42,
    "game": {
      "PTS": 0,
      "MIN": 0,
      "FGP": 0,
      "P3P": 0,
      "FTP": 0,
      "REB": 0,
      "AST": 0,
      "BLK": 0,
      "STL": 0,
      "PF": 0,
      "TO": 0
    },
    "season": {
      "GP": 34,
      "PPG": 3.0,
      "MIN": 18.7,
      "FGP": 38.5,
      "P3P": 26.5,
      "FTP": 76.2,
      "REB": 2.8,
      "AST": 1.3,
      "BLK": 0.5,
      "STL": 0.3,
      "PF": 1.9,
      "TO": 0.7
    },
    "career": {
      "GP": 440,
      "PPG": 6.4,
      "MIN": 22.3,
      "FGP": 44.3,
      "P3P": 35.4,
      "FTP": 77.7,
      "REB": 4.4,
      "AST": 1.2,
      "BLK": 0.9,
      "STL": 0.4,
      "PF": 2.1,
      "TO": 0.7
    }
  },
  {
    "id": 58,
    "name": "Dalton Knecht",
    "image": "../images/players/Knecht.png",
    "jersey": 4,
    "game": {
      "PTS": 13,
      "MIN": 26,
      "FGP": 55.6,
      "P3P": 33.3,
      "FTP": 50.0,
      "REB": 4,
      "AST": 3,
      "BLK": 0,
      "STL": 0,
      "PF": 1,
      "TO": 0
    },
    "season": {
      "GP": 57,
      "PPG": 9.0,
      "MIN": 19.9,
      "FGP": 46.3,
      "P3P": 36.3,
      "FTP": 78.5,
      "REB": 2.9,
      "AST": 0.8,
      "BLK": 0.1,
      "STL": 0.4,
      "PF": 1.3,
      "TO": 0.5
    },
    "career": {
      "GP": 57,
      "PPG": 9.0,
      "MIN": 19.9,
      "FGP": 46.3,
      "P3P": 36.3,
      "FTP": 78.5,
      "REB": 2.9,
      "AST": 0.8,
      "BLK": 0.1,
      "STL": 0.4,
      "PF": 1.3,
      "TO": 0.5
    }
  },
  {
    "id": 59,
    "name": "Christian Koloko",
    "image": "../images/players/Koloko.png",
    "jersey": 10,
    "game": {
      "PTS": 0,
      "MIN": 0,
      "FGP": 0,
      "P3P": 0,
      "FTP": 0,
      "REB": 0,
      "AST": 0,
      "BLK": 0,
      "STL": 0,
      "PF": 0,
      "TO": 0
    },
    "season": {
      "GP": 29,
      "PPG": 2.2,
      "MIN": 8.5,
      "FGP": 65.1,
      "P3P": 0,
      "FTP": 87.5,
      "REB": 2.2,
      "AST": 0.4,
      "BLK": 0.3,
      "STL": 0.2,
      "PF": 1.1,
      "TO": 0.2
    },
    "career": {
      "GP": 87,
      "PPG": 2.8,
      "MIN": 12.0,
      "FGP": 51.8,
      "P3P": 7.1,
      "FTP": 65.7,
      "REB": 2.7,
      "AST": 0.5,
      "BLK": 0.7,
      "STL": 0.3,
      "PF": 1.8,
      "TO": 0.3
    }
  },
  {
    "id": 72,
    "name": "Alex Len",
    "image": "../images/players/Len.png",
    "jersey": 27,
    "game": {
      "PTS": 0,
      "MIN": 5,
      "FGP": 0,
      "P3P": 0,
      "FTP": 0,
      "REB": 0,
      "AST": 0,
      "BLK": 0,
      "STL": 0,
      "PF": 0,
      "TO": 0
    },
    "season": {
      "GP": 40,
      "PPG": 1.4,
      "MIN": 7.4,
      "FGP": 52.2,
      "P3P": 16.7,
      "FTP": 53.8,
      "REB": 1.8,
      "AST": 0.8,
      "BLK": 0.5,
      "STL": 0.2,
      "PF": 1.0,
      "TO": 0.3
    },
    "career": {
      "GP": 684,
      "PPG": 6.7,
      "MIN": 17.1,
      "FGP": 51.0,
      "P3P": 32.2,
      "FTP": 68.0,
      "REB": 5.3,
      "AST": 0.9,
      "BLK": 0.9,
      "STL": 0.4,
      "PF": 2.3,
      "TO": 1.1
    }
  },
  {
    "id": 66,
    "name": "Shake Milton",
    "image": "../images/players/Milton.png",
    "jersey": 20,
    "game": {
      "PTS": 12,
      "MIN": 19,
      "FGP": 71.4,
      "P3P": 50.0,
      "FTP": 0,
      "REB": 2,
      "AST": 2,
      "BLK": 0,
      "STL": 2,
      "PF": 0,
      "TO": 1
    },
    "season": {
      "GP": 46,
      "PPG": 5.9,
      "MIN": 15.3,
      "FGP": 46.7,
      "P3P": 37.5,
      "FTP": 80.0,
      "REB": 1.9,
      "AST": 2.0,
      "BLK": 0.1,
      "STL": 0.4,
      "PF": 1.2,
      "TO": 0.7
    },
    "career": {
      "GP": 348,
      "PPG": 8.2,
      "MIN": 18.9,
      "FGP": 45.2,
      "P3P": 36.0,
      "FTP": 82.5,
      "REB": 2.2,
      "AST": 2.4,
      "BLK": 0.2,
      "STL": 0.5,
      "PF": 1.7,
      "TO": 1.0
    }
  },
  {
    "id": 71,
    "name": "Markieff Morris",
    "image": "../images/players/Morris.png",
    "jersey": 35,
    "game": {
      "PTS": 0,
      "MIN": 0,
      "FGP": 0,
      "P3P": 0,
      "FTP": 0,
      "REB": 0,
      "AST": 0,
      "BLK": 0,
      "STL": 0,
      "PF": 0,
      "TO": 0
    },
    "season": {
      "GP": 10,
      "PPG": 2.3,
      "MIN": 6.1,
      "FGP": 25.0,
      "P3P": 25.0,
      "FTP": 100.0,
      "REB": 0.9,
      "AST": 0.7,
      "BLK": 0.1,
      "STL": 0.1,
      "PF": 0.5,
      "TO": 0.3
    },
    "career": {
      "GP": 786,
      "PPG": 10.2,
      "MIN": 23.4,
      "FGP": 44.4,
      "P3P": 34.2,
      "FTP": 77.9,
      "REB": 4.9,
      "AST": 1.5,
      "BLK": 0.5,
      "STL": 0.8,
      "PF": 2.6,
      "TO": 1.4
    }
  },
  {
    "id": 35,
    "name": "Austin Reaves",
    "image": "../images/players/Reaves.png",
    "jersey": 15,
    "game": {
      "PTS": 0,
      "MIN": 0,
      "FGP": 0,
      "P3P": 0,
      "FTP": 0,
      "REB": 0,
      "AST": 0,
      "BLK": 0,
      "STL": 0,
      "PF": 0,
      "TO": 0
    },
    "season": {
      "GP": 53,
      "PPG": 19.1,  
      "MIN": 34.3,
      "FGP": 44.7,
      "P3P": 36.2,
      "FTP": 86.7,
      "REB": 4.2,
      "AST": 6.0,
      "BLK": 0.3,
      "STL": 1.1,
      "PF": 2.0,
      "TO": 2.4
    },
    "career": {
      "GP": 260,
      "PPG": 13.8,
      "MIN": 29.7,
      "FGP": 48.0,
      "P3P": 36.4,
      "FTP": 85.9,
      "REB": 3.7,
      "AST": 4.2,
      "BLK": 0.3,
      "STL": 0.7,
      "PF": 1.7,
      "TO": 1.7
    }
  },
  {
    "id": 54,
    "name": "Cam Reddish",
    "image": "../images/players/Reddish.png",
    "jersey": 5,
    "game": {
      "PTS": 0,
      "MIN": 0,
      "FGP": 0,
      "P3P": 0,
      "FTP": 0,
      "REB": 0,
      "AST": 0,
      "BLK": 0,
      "STL": 0,
      "PF": 0,
      "TO": 0
    },
    "season": {
      "GP": 31,
      "PPG": 3.3,  
      "MIN": 18.1,
      "FGP": 43.0,
      "P3P": 28.9,
      "FTP": 61.5,
      "REB": 2.0,
      "AST": 0.7,
      "BLK": 0.3,
      "STL": 1.0,
      "PF": 1.4,
      "TO": 0.4
    },
    "career": {
      "GP": 252,
      "PPG": 8.5,  
      "MIN": 23.2,        
      "FGP": 39.9,
      "P3P": 32.2,
      "FTP": 82.1,
      "REB": 2.7,
      "AST": 1.2,
      "BLK": 0.4,
      "STL": 1.0,
      "PF": 1.7,
      "TO": 1.1
    }
  },
  {
    "id": 50,
    "name": "Jarred Vanderbilt",
    "image": "../images/players/Vanderbilt.png",
    "jersey": 2,
    "game": {
      "PTS": 12,
      "MIN": 20,
      "FGP": 57.1,
      "P3P": 50.0,
      "FTP": 100.0,
      "REB": 8,
      "AST": 1,
      "BLK": 2,
      "STL": 1,
      "PF": 2,
      "TO": 0
    },
    "season": {
      "GP": 16,
      "PPG": 4.3,  
      "MIN": 15.8,
      "FGP": 50.0,
      "P3P": 35.0,
      "FTP": 50.0,
      "REB": 5.4,
      "AST": 1.1,
      "BLK": 0.3,
      "STL": 0.9,
      "PF": 1.8,
      "TO": 0.6
    },
    "career": {
      "GP": 289,
      "PPG": 6.0,  
      "MIN": 20.2,        
      "FGP": 56.5,
      "P3P": 29.7,
      "FTP": 63.9,
      "REB": 6.3,
      "AST": 1.4,
      "BLK": 0.4,
      "STL": 1.1,
      "PF": 2.0,
      "TO": 1.0
    }
  },
  {
    "id": 55,
    "name": "Gabe Vincent",
    "image": "../images/players/Walker.png",
    "jersey": 7,
    "game": {
      "PTS": 2,
      "MIN": 29,
      "FGP": 14.3,
      "P3P": 0,
      "FTP": 0,
      "REB": 0,
      "AST": 3,
      "BLK": 0,
      "STL": 2,
      "PF": 0,
      "TO": 0
    },
    "season": {
      "GP": 52,
      "PPG": 5.6,  
      "MIN": 20.6,
      "FGP": 38.0,
      "P3P": 31.8,
      "FTP": 64.3,
      "REB": 1.2,
      "AST": 1.5,
      "BLK": 0.2,
      "STL": 0.8,
      "PF": 2.0,
      "TO": 0.6
    },
    "career": {
      "GP": 258,
      "PPG": 7.1,  
      "MIN": 20.8,        
      "FGP": 39.3,
      "P3P": 32.9,
      "FTP": 83.0,
      "REB": 1.6,
      "AST": 2.1,
      "BLK": 0.1,
      "STL": 0.8,
      "PF": 2.0,
      "TO": 1.0
    }
  }
]